d2_python/__init__.py
d2_python/bin/darwin/d2-bin
d2_python/bin/linux/d2-bin
d2_python/bin/win32/d2-bin.exe
d2_python_wrapper-0.2.0.dist-info/METADATA
d2_python_wrapper-0.2.0.dist-info/WHEEL
d2_python_wrapper-0.2.0.dist-info/top_level.txt
d2_python_wrapper-0.2.0.dist-info/RECORD
