Metadata-Version: 2.1
Name: d2-python-wrapper
Version: 0.2.0
Summary: Python wrapper for D2 diagram tool
Author: Diego Carrasco G.
Requires-Python: >=3.7
